{"AnswerList":{"1":{"QuestionId":1,"AnswerId":4,"AnswerTime":"2020-12-14T13:34:40.7964685+09:00"},"2":{"QuestionId":2,"AnswerId":4,"AnswerTime":"2020-12-14T13:34:40.7964765+09:00"},"3":{"QuestionId":3,"AnswerId":4,"AnswerTime":"2020-12-14T13:34:40.7964788+09:00"},"4":{"QuestionId":4,"AnswerId":3,"AnswerTime":"2020-12-14T13:34:40.7964808+09:00"},"5":{"QuestionId":5,"AnswerId":4,"AnswerTime":"2020-12-14T13:34:40.7964832+09:00"},"6":{"QuestionId":6,"AnswerId":3,"AnswerTime":"2020-12-14T13:34:40.7964851+09:00"},"7":{"QuestionId":7,"AnswerId":1,"AnswerTime":"2020-12-14T13:34:40.7964868+09:00"},"8":{"QuestionId":8,"AnswerId":3,"AnswerTime":"2020-12-14T13:34:40.7964886+09:00"},"9":{"QuestionId":9,"AnswerId":3,"AnswerTime":"2020-12-14T13:34:40.7964908+09:00"},"10":{"QuestionId":10,"AnswerId":4,"AnswerTime":"2020-12-14T13:34:40.7964927+09:00"},"11":{"QuestionId":11,"AnswerId":3,"AnswerTime":"2020-12-14T13:34:40.7964946+09:00"},"12":{"QuestionId":12,"AnswerId":4,"AnswerTime":"2020-12-14T13:34:40.7964964+09:00"},"13":{"QuestionId":13,"AnswerId":2,"AnswerTime":"2020-12-14T13:34:40.7964987+09:00"},"14":{"QuestionId":14,"AnswerId":4,"AnswerTime":"2020-12-14T13:34:40.7965006+09:00"},"15":{"QuestionId":15,"AnswerId":1,"AnswerTime":"2020-12-14T13:34:40.7965023+09:00"},"16":{"QuestionId":16,"AnswerId":1,"AnswerTime":"2020-12-14T13:34:40.796504+09:00"},"17":{"QuestionId":17,"AnswerId":3,"AnswerTime":"2020-12-14T13:34:40.7965059+09:00"},"18":{"QuestionId":18,"AnswerId":4,"AnswerTime":"2020-12-14T13:34:40.7965076+09:00"},"19":{"QuestionId":19,"AnswerId":3,"AnswerTime":"2020-12-14T13:34:40.7965109+09:00"},"20":{"QuestionId":20,"AnswerId":1,"AnswerTime":"2020-12-14T13:34:40.7965127+09:00"},"21":{"QuestionId":21,"AnswerId":2,"AnswerTime":"2020-12-14T13:34:40.7965145+09:00"},"22":{"QuestionId":22,"AnswerId":1,"AnswerTime":"2020-12-14T13:34:40.7965161+09:00"},"23":{"QuestionId":23,"AnswerId":1,"AnswerTime":"2020-12-14T13:34:40.7965179+09:00"},"24":{"QuestionId":24,"AnswerId":2,"AnswerTime":"2020-12-14T13:34:40.7965196+09:00"},"25":{"QuestionId":25,"AnswerId":3,"AnswerTime":"2020-12-14T13:34:40.7965213+09:00"},"26":{"QuestionId":26,"AnswerId":4,"AnswerTime":"2020-12-14T13:34:40.796523+09:00"},"27":{"QuestionId":27,"AnswerId":2,"AnswerTime":"2020-12-14T13:34:40.7965247+09:00"},"28":{"QuestionId":28,"AnswerId":2,"AnswerTime":"2020-12-14T13:34:40.7965264+09:00"},"29":{"QuestionId":29,"AnswerId":3,"AnswerTime":"2020-12-14T13:34:40.7965282+09:00"},"30":{"QuestionId":30,"AnswerId":4,"AnswerTime":"2020-12-14T13:34:40.7965299+09:00"},"31":{"QuestionId":31,"AnswerId":1,"AnswerTime":"2020-12-14T13:34:40.7965316+09:00"},"32":{"QuestionId":32,"AnswerId":4,"AnswerTime":"2020-12-14T13:34:40.7965333+09:00"},"33":{"QuestionId":33,"AnswerId":1,"AnswerTime":"2020-12-14T13:34:40.7965351+09:00"},"34":{"QuestionId":34,"AnswerId":1,"AnswerTime":"2020-12-14T13:34:40.7965368+09:00"},"35":{"QuestionId":35,"AnswerId":3,"AnswerTime":"2020-12-14T13:34:40.7965385+09:00"},"36":{"QuestionId":36,"AnswerId":1,"AnswerTime":"2020-12-14T13:34:40.7965402+09:00"},"37":{"QuestionId":37,"AnswerId":2,"AnswerTime":"2020-12-14T13:34:40.7965419+09:00"},"38":{"QuestionId":38,"AnswerId":4,"AnswerTime":"2020-12-14T13:34:40.7965437+09:00"},"39":{"QuestionId":39,"AnswerId":3,"AnswerTime":"2020-12-14T13:34:40.7965459+09:00"},"40":{"QuestionId":40,"AnswerId":4,"AnswerTime":"2020-12-14T13:34:40.7965476+09:00"},"41":{"QuestionId":41,"AnswerId":3,"AnswerTime":"2020-12-14T13:34:40.7965493+09:00"},"42":{"QuestionId":42,"AnswerId":3,"AnswerTime":"2020-12-14T13:34:40.7965509+09:00"},"43":{"QuestionId":43,"AnswerId":4,"AnswerTime":"2020-12-14T13:34:40.7965536+09:00"},"44":{"QuestionId":44,"AnswerId":2,"AnswerTime":"2020-12-14T13:34:40.7965553+09:00"},"45":{"QuestionId":45,"AnswerId":2,"AnswerTime":"2020-12-14T13:34:40.796557+09:00"},"46":{"QuestionId":46,"AnswerId":1,"AnswerTime":"2020-12-14T13:34:40.7965587+09:00"},"47":{"QuestionId":47,"AnswerId":2,"AnswerTime":"2020-12-14T13:34:40.7965608+09:00"},"48":{"QuestionId":48,"AnswerId":4,"AnswerTime":"2020-12-14T13:34:40.7965625+09:00"},"49":{"QuestionId":49,"AnswerId":3,"AnswerTime":"2020-12-14T13:34:40.7965643+09:00"},"50":{"QuestionId":50,"AnswerId":2,"AnswerTime":"2020-12-14T13:34:40.796566+09:00"}},"IsSubmit":true,"SubmitTime":"2020-12-14T10:57:27.7947649+09:00"}